knows/__init__.py
knows/__main__.py
knows/command_line_interface.py
knows/graph.py
knows/graph_drawer.py
knows/output_format.py
knows/schema.json
knows/schema.py
knows-3.0.0.dist-info/licenses/LICENSE
knows-3.0.0.dist-info/METADATA
knows-3.0.0.dist-info/WHEEL
knows-3.0.0.dist-info/entry_points.txt
knows-3.0.0.dist-info/top_level.txt
knows-3.0.0.dist-info/RECORD
