Metadata-Version: 2.4
Name: knows
Version: 3.0.0
Summary: Powerful and user-friendly property graph generator that creates graphs with specified node and edge numbers, supporting multiple output formats, schema files and visualization
Author-email: Łukasz Szeremeta <l.szeremeta.dev+knows@gmail.com>
License-Expression: MIT
Project-URL: Homepage, https://github.com/lszeremeta/knows
Project-URL: Repository, https://github.com/lszeremeta/knows
Project-URL: Issues, https://github.com/lszeremeta/knows/issues
Project-URL: Changelog, https://github.com/lszeremeta/knows/releases
Keywords: knows,generator,graph generator,benchmark,yarspg,graphs,mathematics,CLI,GraphML,YARS-PG,property graph,graph,graph database,graph data,Neo4j,NetworkX,Faker,graph analysis,benchmarking,graph visualization,data science,graph algorithms,network analysis,graph tool,data analytics,educational tool,research tool,graph generation,python graph,docker graph tool,command line interface,CLI tool,json,svg,data visualization
Classifier: Development Status :: 5 - Production/Stable
Classifier: Environment :: Console
Classifier: Intended Audience :: Education
Classifier: Intended Audience :: Developers
Classifier: Intended Audience :: Information Technology
Classifier: Intended Audience :: Science/Research
Classifier: Natural Language :: English
Classifier: Operating System :: MacOS
Classifier: Operating System :: OS Independent
Classifier: Operating System :: POSIX :: Linux
Classifier: Programming Language :: Python
Classifier: Programming Language :: Python :: 3
Classifier: Programming Language :: Python :: 3 :: Only
Classifier: Programming Language :: Python :: 3.10
Classifier: Programming Language :: Python :: 3.11
Classifier: Programming Language :: Python :: 3.12
Classifier: Programming Language :: Python :: 3.13
Classifier: Programming Language :: Python :: 3.14
Classifier: Topic :: System :: Benchmark
Classifier: Topic :: Database
Classifier: Topic :: File Formats
Classifier: Topic :: Internet
Classifier: Topic :: Multimedia :: Graphics :: Presentation
Classifier: Topic :: Multimedia :: Graphics :: Viewers
Classifier: Topic :: Scientific/Engineering
Classifier: Topic :: Scientific/Engineering :: Information Analysis
Classifier: Topic :: Scientific/Engineering :: Mathematics
Classifier: Topic :: Utilities
Classifier: Typing :: Typed
Requires-Python: >=3.10
License-File: LICENSE
Requires-Dist: networkx>=3.4.0
Requires-Dist: Faker>=36.0.0
Requires-Dist: jsonschema>=4.22.0
Provides-Extra: draw
Requires-Dist: matplotlib>=3.10.0; extra == "draw"
Requires-Dist: scipy>=1.14.0; extra == "draw"
Provides-Extra: test
Requires-Dist: matplotlib>=3.10.0; extra == "test"
Requires-Dist: scipy>=1.14.0; extra == "test"
Requires-Dist: pytest>=8.4.0; extra == "test"
Requires-Dist: flake8>=7.0.0; extra == "test"
Provides-Extra: dev
Requires-Dist: matplotlib>=3.10.0; extra == "dev"
Requires-Dist: scipy>=1.14.0; extra == "dev"
Requires-Dist: pytest>=8.4.0; extra == "dev"
Requires-Dist: flake8>=7.0.0; extra == "dev"
Dynamic: license-file
